pymode/__init__.py
pymode/client.py
pymode/version.py
pymode-1.3.0.dist-info/LICENSE.txt
pymode-1.3.0.dist-info/METADATA
pymode-1.3.0.dist-info/WHEEL
pymode-1.3.0.dist-info/top_level.txt
pymode-1.3.0.dist-info/RECORD
