Metadata-Version: 2.1
Name: pymode
Version: 1.3.0
Summary: A python client for typed interactions with the Mode Analytics API.
Home-page: https://github.com/dwallace0723/pymode
Author: David Wallace
Author-email: dwallace0723@gmail.com
License: MIT
Keywords: mode analytics python
Platform: UNKNOWN
Classifier: License :: OSI Approved :: MIT License
Classifier: Development Status :: 5 - Production/Stable
Classifier: Natural Language :: English
Classifier: Topic :: Software Development
Classifier: Intended Audience :: Developers
Classifier: Operating System :: OS Independent
Classifier: Programming Language :: Python :: 3 :: Only
Classifier: Programming Language :: Python :: 3.6
Classifier: Programming Language :: Python :: 3.7
Classifier: Programming Language :: Python :: 3.8
Requires-Python: >=3.6
Requires-Dist: requests (>=2.22.0)
Requires-Dist: attrs (>=19.3.0)
